cilicili_ai/__init__.py
cilicili_ai/decorators.py
cilicili_ai-0.0.2.dist-info/METADATA
cilicili_ai-0.0.2.dist-info/WHEEL
cilicili_ai-0.0.2.dist-info/top_level.txt
cilicili_ai-0.0.2.dist-info/RECORD
