Metadata-Version: 2.1
Name: cilicili-ai
Version: 0.0.2
Summary: A task management decorator for Cilicili AI service.
Author: Amiee
Author-email: 1223411083@qq.com
Classifier: Programming Language :: Python :: 3
Classifier: License :: OSI Approved :: MIT License
Classifier: Operating System :: OS Independent
Requires-Python: >=3.7
Requires-Dist: requests
